xcube_gedidb/__init__.py
xcube_gedidb/constant.py
xcube_gedidb/plugin.py
xcube_gedidb/store.py
xcube_gedidb/utils.py
xcube_gedidb/version.py
xcube_gedidb-0.1.1.dist-info/licenses/LICENSE
xcube_gedidb-0.1.1.dist-info/licenses/NOTICE
xcube_gedidb-0.1.1.dist-info/METADATA
xcube_gedidb-0.1.1.dist-info/WHEEL
xcube_gedidb-0.1.1.dist-info/top_level.txt
xcube_gedidb-0.1.1.dist-info/RECORD
