Metadata-Version: 2.4
Name: xcube_gedidb
Version: 0.1.1
Summary: xcube datastore for accessing GediDB datastore using the `gedidb` API
Author-email: Yogesh Kumar Baljeet Singh <yogesh.baljeetsingh@brockmann-consult.de>
License: MIT
Project-URL: Repository, https://github.com/xcube-dev/xcube-gedidb
Project-URL: Issues, https://github.com/xcube-dev/xcube-gedidb/issues
Project-URL: Changelog, https://github.com/xcube-dev/xcube-gedidb/blob/main/CHANGES.md
Keywords: analysis ready data,data science,datacube,xarray,zarr,xcube,gedi,gedidb
Requires-Python: >=3.10
License-File: LICENSE
License-File: NOTICE
Requires-Dist: xarray
Requires-Dist: xcube-core
Requires-Dist: gedidb
Provides-Extra: dev
Requires-Dist: pytest; extra == "dev"
Requires-Dist: pytest-cov; extra == "dev"
Requires-Dist: pytest-recording; extra == "dev"
Requires-Dist: flake8; extra == "dev"
Dynamic: license-file
